pycorner/.version
pycorner/__init__.py
pycorner/cbc.py
pycorner/corner.py
pycorner/distribution.py
pycorner/misc.py
pycorner-0.0.0.dist-info/LICENSE
pycorner-0.0.0.dist-info/METADATA
pycorner-0.0.0.dist-info/WHEEL
pycorner-0.0.0.dist-info/top_level.txt
pycorner-0.0.0.dist-info/RECORD
